scorep_db/__init__.py
scorep_db/__main__.py
scorep_db/command_add.py
scorep_db/command_clear.py
scorep_db/command_download.py
scorep_db/command_get_id.py
scorep_db/command_health_check.py
scorep_db/command_merge.py
scorep_db/command_parse.py
scorep_db/command_query.py
scorep_db/command_status.py
scorep_db/config.py
scorep_db/exceptions.py
scorep_db/figures/scorep-db-overview.png
scorep_db/object_store.py
scorep_db/rdf_database.py
scorep_db/rdf_helper.py
scorep_db-0.2.0.dist-info/LICENSE
scorep_db-0.2.0.dist-info/METADATA
scorep_db-0.2.0.dist-info/WHEEL
scorep_db-0.2.0.dist-info/entry_points.txt
scorep_db-0.2.0.dist-info/RECORD
