Metadata-Version: 2.3
Name: scorep-db
Version: 0.2.0
Summary: Minimal tooling to keep track of Score-P Profiles + Traces.
Author: Maximilian Sander
Author-email: maximilian.sander1@tu-dresden.de
Requires-Python: >=3.10,<4
Classifier: Programming Language :: Python :: 3
Classifier: Programming Language :: Python :: 3.10
Classifier: Programming Language :: Python :: 3.11
Classifier: Programming Language :: Python :: 3.12
Classifier: Programming Language :: Python :: 3.13
Requires-Dist: minio (>=7.2.14,<7.3.0)
Requires-Dist: psycopg2-binary (>=2.9.10,<2.10.0)
Requires-Dist: python-dotenv (>=1.0.1,<1.1.0)
Requires-Dist: rdflib (>=7.1.2,<7.2.0)
Requires-Dist: rdflib-sqlalchemy (>=0.5.4,<0.6.0)
Requires-Dist: setuptools (>=75.8.0,<75.9.0)
Requires-Dist: sparqlwrapper (>=2.0.0,<2.1.0)
Project-URL: Homepage, https://gitlab.hrz.tu-chemnitz.de/s0872522--tu-dresden.de/scorep-db
Project-URL: Repository, https://gitlab.hrz.tu-chemnitz.de/s0872522--tu-dresden.de/scorep-db
